INSTALL.rst
LICENSE.txt
MANIFEST.in
README.rst
RELEASES.rst
TODO.rst
setup.cfg
setup.py
examples/ifsf-write.cli
examples/ifsf.cli
examples/kjv-write.cli
examples/kjv.cli
examples/shakespeare-write.cli
examples/shakespeare.cli
examples/timecube-write.cli
examples/timecube.cli
examples/warpeace-write.cli
examples/warpeace.cli
samyro/__init__.py
samyro/integerize.py
samyro/learn.py
samyro/model.py
samyro/read.py
samyro/write.py
samyro/cli/__init__.py
samyro/cli/learn.py
samyro/cli/sample.py
samyro/cli/shared.py
samyro/cli/write.py
tests/__init__.py
tests/automate.sh
tests/test_load.py
tests/test_read.py
tests/test_write.py